piencrypt/__init__.py
piencrypt/pie.py
piencrypt/piencrypt.py
piencrypt-0.7.5.6.dist-info/LICENSE
piencrypt-0.7.5.6.dist-info/METADATA
piencrypt-0.7.5.6.dist-info/WHEEL
piencrypt-0.7.5.6.dist-info/top_level.txt
piencrypt-0.7.5.6.dist-info/RECORD
