Metadata-Version: 2.1
Name: piencrypt
Version: 0.7.5.6
Summary: Encrypt your crucial data into Image file
Home-page: UNKNOWN
Author: Throttlerz (Siddhartha Roy)
Author-email: <sid86harth@gmail.com>
License: UNKNOWN
Keywords: python,image processing,encrypt,decrypt,hide messages,data store
Platform: UNKNOWN
Classifier: Development Status :: 1 - Planning
Classifier: Intended Audience :: Developers
Classifier: Programming Language :: Python :: 3
Classifier: Operating System :: Unix
Classifier: Operating System :: MacOS :: MacOS X
Classifier: Operating System :: Microsoft :: Windows
License-File: LICENSE
Requires-Dist: cryptography
